carnival/__init__.py
carnival/__main__.py
carnival/cli.py
carnival/contrib/__init__.py
carnival/contrib/steps/__init__.py
carnival/contrib/steps/apt.py
carnival/contrib/steps/docker.py
carnival/contrib/steps/docker_compose.py
carnival/contrib/steps/fs.py
carnival/contrib/steps/ssh.py
carnival/contrib/steps/system.py
carnival/contrib/steps/systemd/__init__.py
carnival/contrib/steps/systemd/journald/__init__.py
carnival/contrib/steps/systemd/journald/journald.conf
carnival/contrib/steps/transfer.py
carnival/hosts/__init__.py
carnival/hosts/base/__init__.py
carnival/hosts/base/connection.py
carnival/hosts/base/host.py
carnival/hosts/base/result.py
carnival/hosts/base/result_promise.py
carnival/hosts/base/stat_result.py
carnival/hosts/local/__init__.py
carnival/hosts/local/connection.py
carnival/hosts/local/result_promise.py
carnival/hosts/ssh/__init__.py
carnival/hosts/ssh/connection.py
carnival/hosts/ssh/result_promise.py
carnival/hosts/ssh/ssh_config.py
carnival/internal_tasks.py
carnival/plugins.py
carnival/py.typed
carnival/role.py
carnival/steps/__init__.py
carnival/steps/_validator_cache.py
carnival/steps/shortcuts.py
carnival/steps/step.py
carnival/steps/validators.py
carnival/task.py
carnival/tasks_loader.py
carnival/templates.py
carnival/utils.py
carnival-4.0.1.dist-info/entry_points.txt
carnival-4.0.1.dist-info/LICENSE
carnival-4.0.1.dist-info/WHEEL
carnival-4.0.1.dist-info/METADATA
carnival-4.0.1.dist-info/RECORD
