Metadata-Version: 2.1
Name: carnival
Version: 4.0.1
Summary: Software provisioning tool
License: MIT
Author: Dmirty Simonov
Author-email: demalf@gmail.com
Requires-Python: >=3.8,<4.0
Classifier: License :: OSI Approved :: MIT License
Classifier: Programming Language :: Python :: 3
Classifier: Programming Language :: Python :: 3.8
Classifier: Programming Language :: Python :: 3.9
Requires-Dist: Click (==8.0.3)
Requires-Dist: Jinja2 (==3.0.3)
Requires-Dist: colorama (>=0.4.4,<0.5.0)
Requires-Dist: paramiko (>=2.8.1,<3.0.0)
Requires-Dist: python-dotenv (==0.19.2)
Requires-Dist: tqdm (>=4.62.3,<5.0.0)
